kertash/__init__.py
kertash/core.py
kertash/lib/__init__.py
kertash/lib/analyze.py
kertash-0.1.5.dist-info/METADATA
kertash-0.1.5.dist-info/WHEEL
kertash-0.1.5.dist-info/licenses/LICENSE
kertash-0.1.5.dist-info/RECORD
